citros_meta.py
bin/__init__.py
bin/cli.py
bin/cli_impl.py
citros/__init__.py
citros/citros.py
citros/citros_batch.py
citros/citros_events.py
citros/citros_params.py
citros/citros_utils.py
citros/launches/__init__.py
citros/launches/launch.py
citros/logger/__init__.py
citros/logger/logger.py
citros/parsers/__init__.py
citros/parsers/parser_base.py
citros/parsers/parser_ros2.py
citros_test-1.2.73.data/scripts/citros
data/__init__.py
data/defaults/__init__.py
data/defaults/default_flow.json
data/defaults/default_settings.json
data/defaults/default_simulation.json
data/markdown/README_foxglove.md
data/markdown/README_functions.md
data/markdown/README_notebooks.md
data/markdown/README_parameter_setups.md
data/markdown/README_reports.md
data/markdown/README_simulations.md
data/markdown/README_workflows.md
data/markdown/__init__.py
data/misc/.citrosignore
data/misc/__init__.py
data/sample_code/__init__.py
data/sample_code/my_func.py
data/schemas/__init__.py
data/schemas/schema_flow.json
data/schemas/schema_param_setup.json
data/schemas/schema_settings.json
data/schemas/schema_simulation.json
data/scripts/__init__.py
data/scripts/ssh_agent_on_login.sh
tests/__init__.py
tests/test_evaluate_dictionary.py
tests/test_parse_makefile.py
tests/test_parse_setup_py.py
tests/test_parse_xml.py
tests/unittest_wrapper.py
citros_test-1.2.73.dist-info/LICENSE
citros_test-1.2.73.dist-info/METADATA
citros_test-1.2.73.dist-info/WHEEL
citros_test-1.2.73.dist-info/top_level.txt
citros_test-1.2.73.dist-info/RECORD
