Metadata-Version: 2.1
Name: citros-test
Version: 1.2.73
Summary: A cli entrypoint for the citros system.
Home-page: https://citros.io
Author: shalev
Author-email: shalev@lulav.space
License: LICENSE
Project-URL: Documentation, http://citros.io/doc/docs_cli
Project-URL: Source Code, https://github.com/lulav/citros_cli
Project-URL: Bug Tracker, https://github.com/lulav/citros_cli/issues
License-File: LICENSE
Requires-Dist: ansicolors
Requires-Dist: gql
Requires-Dist: graphql-core
Requires-Dist: requests
Requires-Dist: rosdep
Requires-Dist: python-decouple
Requires-Dist: requests-toolbelt
Requires-Dist: soupsieve
Requires-Dist: bs4
Requires-Dist: zipp
Requires-Dist: pyjwt
Requires-Dist: psycopg2-binary
Requires-Dist: urllib3
Requires-Dist: InquirerPy
Requires-Dist: GitPython
Requires-Dist: jsonschema
Requires-Dist: cryptography
Requires-Dist: numpy
Requires-Dist: psutil
Requires-Dist: cmakeast
Requires-Dist: opentelemetry-api
Requires-Dist: opentelemetry-sdk
Requires-Dist: opentelemetry-exporter-otlp-proto-grpc
Requires-Dist: pydantic ==1.10.12
Requires-Dist: python-on-whales
Requires-Dist: importlib-resources
Requires-Dist: citros-data-analysis
